{
    "glue": {
        "worker": "./worker.js",
        "layouts": {
            "autoRestore": false,
            "autoSaveWindowContext": false
        },
        "channels": true,
        "appManager": true,
        "application": "TestRunner"
    },
    "gateway": {
        "location": "./gateway.js"
    },
    "channels": [
        {
            "name": "Red",
            "meta": {
                "color": "red"
            },
            "data": {}
        },
        {
            "name": "Green",
            "meta": {
                "color": "green"
            },
            "data": {}
        },
        {
            "name": "Blue",
            "meta": {
                "color": "blue"
            },
            "data": {}
        },
        {
            "name": "Pink",
            "meta": {
                "color": "pink"
            },
            "data": {}
        },
        {
            "name": "Yellow",
            "meta": {
                "color": "yellow"
            },
            "data": {}
        }
    ],
    "appManager": {
        "localApplications": [
            {
                "name": "dummyApp",
                "details": {
                    "url": "http://localhost:9999/dummyApp"
                }
            },
            {
                "name": "coreSupport",
                "details": {
                    "url": "http://localhost:9999/coreSupport"
                }
            },
            {
                "name": "Test",
                "details": {
                    "url": "http://localhost:9999"
                }
            },
            {
                "name": "AppWithDetails-local",
                "title": "AppWithDetails-title",
                "version": "AppWithDetails-version",
                "details": {
                    "url": "https://glue42.com/",
                    "context": {
                        "b": 98
                    },
                    "width": 400,
                    "height": 400,
                    "top": 100,
                    "left": 100
                },
                "customProperties": {
                    "a": 97
                }
            }
        ]
    }
}
